autolatex/__init__.py
autolatex/table.py
autolatex/equation/__init__.py
autolatex/equation/average.py
autolatex/equation/fitting.py
autolatex/equation/stdev.py
autolatex/word2tex/__init__.py
autolatex/word2tex/config.py
autolatex/word2tex/config_sample.py
autolatex/word2tex/modify_re.py
autolatex/word2tex/templates.py
autolatex/word2tex/word2tex.py
autolatex-0.1.7.dist-info/LICENSE
autolatex-0.1.7.dist-info/METADATA
autolatex-0.1.7.dist-info/WHEEL
autolatex-0.1.7.dist-info/entry_points.txt
autolatex-0.1.7.dist-info/top_level.txt
autolatex-0.1.7.dist-info/RECORD
