Metadata-Version: 2.1
Name: autolatex
Version: 0.1.7
Summary: Generate LaTeX code by Python.
Home-page: https://github.com/Benature/AutoLaTeX
Author: Benature Wang
Author-email: wbenature@163.com
License: UNKNOWN
Platform: UNKNOWN
Classifier: Programming Language :: Python :: 3.7
Classifier: License :: OSI Approved :: MIT License
Classifier: Operating System :: OS Independent
Requires-Dist: pandas
Requires-Dist: numpy
Requires-Dist: pyperclip
